satori_docs-1.4.7.dist-info/METADATA
satori_docs-1.4.7.dist-info/WHEEL
satori_docs-1.4.7.dist-info/entry_points.txt
satori_docs-1.4.7.dist-info/licenses/LICENSE
satori_help/__init__.py
satori_help/docs/.vitepress/config.mjs
satori_help/docs/.vitepress/theme/CustomLayout.vue
satori_help/docs/.vitepress/theme/custom.css
satori_help/docs/.vitepress/theme/index.js
satori_help/docs/README.md
satori_help/docs/_sidebar.md
satori_help/docs/cheatsheet.md
satori_help/docs/getting-started/execution-data.md
satori_help/docs/getting-started/hello_world.md
satori_help/docs/getting-started/img/code_example.png
satori_help/docs/getting-started/img/dast_output.png
satori_help/docs/getting-started/img/execution-data_1.png
satori_help/docs/getting-started/img/execution-data_2.png
satori_help/docs/getting-started/img/execution-data_3.png
satori_help/docs/getting-started/img/execution-data_4.png
satori_help/docs/getting-started/img/execution-data_5.png
satori_help/docs/getting-started/img/hello_01.png
satori_help/docs/getting-started/img/hello_02.png
satori_help/docs/getting-started/img/hello_03.png
satori_help/docs/getting-started/img/hello_04.png
satori_help/docs/getting-started/img/install_1.png
satori_help/docs/getting-started/img/install_2.png
satori_help/docs/getting-started/img/playbooks_1.png
satori_help/docs/getting-started/img/playbooks_2.png
satori_help/docs/getting-started/img/sast.png
satori_help/docs/getting-started/install.md
satori_help/docs/getting-started/playbooks.md
satori_help/docs/google75c776a04281401d.html
satori_help/docs/img/dashboard_1.png
satori_help/docs/img/notif_1.png
satori_help/docs/img/notif_2.png
satori_help/docs/img/notif_3.png
satori_help/docs/img/notif_4.png
satori_help/docs/img/notif_5.png
satori_help/docs/img/notif_6.png
satori_help/docs/img/notif_7.png
satori_help/docs/img/notif_telegram_1.png
satori_help/docs/img/notif_telegram_2.png
satori_help/docs/img/repo_1.png
satori_help/docs/img/repo_2.png
satori_help/docs/img/repo_3.png
satori_help/docs/img/repo_4-1.png
satori_help/docs/img/repo_4-2.png
satori_help/docs/img/repo_6.png
satori_help/docs/img/repo_7.png
satori_help/docs/img/repo_8.png
satori_docs-1.4.7.dist-info/RECORD
