Metadata-Version: 2.1
Name: satori-docs
Version: 1.4.7
Summary: Satori CI - Automated Testing
Author-Email: Satori CI <info@satori.ci>
License:                     GNU GENERAL PUBLIC LICENSE
Project-URL: Homepage, https://www.satori.ci
Requires-Python: >=3.9
Requires-Dist: textual>=0.27.0
